{
  "current": {

  },
  "daily": {
    "summary": "Clear throughout the day.",
    "icon": "clear-day",
    "data": [
      {
        "time": 1506225600,
        "summary": "Clear throughout the day.",
        "icon": "clear-day",
        "sunriseTime": 1506250003,
        "sunsetTime": 1506293478,
        "moonPhase": 0.15,
        "precipIntensity": 0,
        "precipIntensityMax": 0.0007,
        "precipIntensityMaxTime": 1506308400,
        "precipProbability": 0,
        "temperatureHigh": 89,
        "temperatureHighTime": 1506279600,
        "temperatureLow": 70.77,
        "temperatureLowTime": 1506337200,
        "apparentTemperatureHigh": 91.24,
        "apparentTemperatureHighTime": 1506279600,
        "apparentTemperatureLow": 71.36,
        "apparentTemperatureLowTime": 1506337200,
        "dewPoint": 62.92,
        "humidity": 0.64,
        "pressure": 1017.27,
        "windSpeed": 0.13,
        "windGust": 6.13,
        "windGustTime": 1506308400,
        "windBearing": 79,
        "cloudCover": 0,
        "uvIndex": 6,
        "uvIndexTime": 1506272400,
        "visibility": 10,
        "ozone": 271.24,
        "temperatureMin": 65.41,
        "temperatureMinTime": 1506247200,
        "temperatureMax": 89,
        "temperatureMaxTime": 1506279600,
        "apparentTemperatureMin": 65.41,
        "apparentTemperatureMinTime": 1506247200,
        "apparentTemperatureMax": 91.24,
        "apparentTemperatureMaxTime": 1506279600
      },
      {
        "time": 1506312000,
        "summary": "Partly cloudy overnight.",
        "icon": "partly-cloudy-night",
        "sunriseTime": 1506336462,
        "sunsetTime": 1506379776,
        "moonPhase": 0.18,
        "precipIntensity": 0.0003,
        "precipIntensityMax": 0.0014,
        "precipIntensityMaxTime": 1506319200,
        "precipProbability": 0.09,
        "precipType": "rain",
        "temperatureHigh": 87.45,
        "temperatureHighTime": 1506366000,
        "temperatureLow": 69.2,
        "temperatureLowTime": 1506423600,
        "apparentTemperatureHigh": 88.94,
        "apparentTemperatureHighTime": 1506366000,
        "apparentTemperatureLow": 69.98,
        "apparentTemperatureLowTime": 1506423600,
        "dewPoint": 64.45,
        "humidity": 0.66,
        "pressure": 1016.87,
        "windSpeed": 4.14,
        "windGust": 10.81,
        "windGustTime": 1506384000,
        "windBearing": 112,
        "cloudCover": 0.12,
        "uvIndex": 5,
        "uvIndexTime": 1506355200,
        "visibility": 10,
        "ozone": 263.22,
        "temperatureMin": 70.77,
        "temperatureMinTime": 1506337200,
        "temperatureMax": 87.45,
        "temperatureMaxTime": 1506366000,
        "apparentTemperatureMin": 71.36,
        "apparentTemperatureMinTime": 1506337200,
        "apparentTemperatureMax": 88.94,
        "apparentTemperatureMaxTime": 1506366000
      },
      {
        "time": 1506398400,
        "summary": "Partly cloudy throughout the day.",
        "icon": "partly-cloudy-day",
        "sunriseTime": 1506422921,
        "sunsetTime": 1506466074,
        "moonPhase": 0.21,
        "precipIntensity": 0.0004,
        "precipIntensityMax": 0.0011,
        "precipIntensityMaxTime": 1506416400,
        "precipProbability": 0.12,
        "precipType": "rain",
        "temperatureHigh": 82.72,
        "temperatureHighTime": 1506452400,
        "temperatureLow": 71.05,
        "temperatureLowTime": 1506510000,
        "apparentTemperatureHigh": 84.66,
        "apparentTemperatureHighTime": 1506452400,
        "apparentTemperatureLow": 72.06,
        "apparentTemperatureLowTime": 1506510000,
        "dewPoint": 65.88,
        "humidity": 0.75,
        "pressure": 1015.57,
        "windSpeed": 5.1,
        "windGust": 8.79,
        "windGustTime": 1506459600,
        "windBearing": 85,
        "cloudCover": 0.41,
        "uvIndex": 4,
        "uvIndexTime": 1506441600,
        "visibility": 10,
        "ozone": 255.42,
        "temperatureMin": 69.2,
        "temperatureMinTime": 1506423600,
        "temperatureMax": 82.72,
        "temperatureMaxTime": 1506452400,
        "apparentTemperatureMin": 69.98,
        "apparentTemperatureMinTime": 1506423600,
        "apparentTemperatureMax": 84.66,
        "apparentTemperatureMaxTime": 1506452400
      },
      {
        "time": 1506484800,
        "summary": "Light rain starting in the afternoon, continuing until evening.",
        "icon": "rain",
        "sunriseTime": 1506509380,
        "sunsetTime": 1506552373,
        "moonPhase": 0.24,
        "precipIntensity": 0.0064,
        "precipIntensityMax": 0.0376,
        "precipIntensityMaxTime": 1506546000,
        "precipProbability": 0.35,
        "precipType": "rain",
        "temperatureHigh": 80.73,
        "temperatureHighTime": 1506535200,
        "temperatureLow": 71.5,
        "temperatureLowTime": 1506578400,
        "apparentTemperatureHigh": 83.32,
        "apparentTemperatureHighTime": 1506535200,
        "apparentTemperatureLow": 72.45,
        "apparentTemperatureLowTime": 1506578400,
        "dewPoint": 67.73,
        "humidity": 0.79,
        "pressure": 1011.69,
        "windSpeed": 5.9,
        "windGust": 10.47,
        "windGustTime": 1506520800,
        "windBearing": 62,
        "cloudCover": 0.52,
        "uvIndex": 4,
        "uvIndexTime": 1506528000,
        "visibility": 10,
        "ozone": 252.73,
        "temperatureMin": 71.05,
        "temperatureMinTime": 1506510000,
        "temperatureMax": 80.73,
        "temperatureMaxTime": 1506535200,
        "apparentTemperatureMin": 72.06,
        "apparentTemperatureMinTime": 1506510000,
        "apparentTemperatureMax": 83.32,
        "apparentTemperatureMaxTime": 1506535200
      },
      {
        "time": 1506571200,
        "summary": "Clear throughout the day.",
        "icon": "clear-day",
        "sunriseTime": 1506595840,
        "sunsetTime": 1506638671,
        "moonPhase": 0.27,
        "precipIntensity": 0.0001,
        "precipIntensityMax": 0.0011,
        "precipIntensityMaxTime": 1506571200,
        "precipProbability": 0.08,
        "precipType": "rain",
        "temperatureHigh": 82.78,
        "temperatureHighTime": 1506625200,
        "temperatureLow": 63.47,
        "temperatureLowTime": 1506682800,
        "apparentTemperatureHigh": 82.78,
        "apparentTemperatureHighTime": 1506625200,
        "apparentTemperatureLow": 63.47,
        "apparentTemperatureLowTime": 1506682800,
        "dewPoint": 57.27,
        "humidity": 0.57,
        "pressure": 1008.71,
        "windSpeed": 10.1,
        "windGust": 23.29,
        "windGustTime": 1506646800,
        "windBearing": 356,
        "cloudCover": 0.05,
        "uvIndex": 6,
        "uvIndexTime": 1506618000,
        "ozone": 253.84,
        "temperatureMin": 68.55,
        "temperatureMinTime": 1506654000,
        "temperatureMax": 82.78,
        "temperatureMaxTime": 1506625200,
        "apparentTemperatureMin": 68.55,
        "apparentTemperatureMinTime": 1506654000,
        "apparentTemperatureMax": 82.78,
        "apparentTemperatureMaxTime": 1506625200
      },
      {
        "time": 1506657600,
        "summary": "Clear throughout the day.",
        "icon": "clear-day",
        "sunriseTime": 1506682299,
        "sunsetTime": 1506724970,
        "moonPhase": 0.3,
        "precipIntensity": 0,
        "precipIntensityMax": 0.0001,
        "precipIntensityMaxTime": 1506664800,
        "precipProbability": 0,
        "temperatureHigh": 76.98,
        "temperatureHighTime": 1506715200,
        "temperatureLow": 59.09,
        "temperatureLowTime": 1506769200,
        "apparentTemperatureHigh": 76.98,
        "apparentTemperatureHighTime": 1506715200,
        "apparentTemperatureLow": 59.09,
        "apparentTemperatureLowTime": 1506769200,
        "dewPoint": 43.19,
        "humidity": 0.41,
        "pressure": 1014.91,
        "windSpeed": 5.45,
        "windGust": 25.85,
        "windGustTime": 1506740400,
        "windBearing": 358,
        "cloudCover": 0.04,
        "uvIndex": 5,
        "uvIndexTime": 1506700800,
        "ozone": 268.13,
        "temperatureMin": 62.67,
        "temperatureMinTime": 1506740400,
        "temperatureMax": 76.98,
        "temperatureMaxTime": 1506715200,
        "apparentTemperatureMin": 62.67,
        "apparentTemperatureMinTime": 1506740400,
        "apparentTemperatureMax": 76.98,
        "apparentTemperatureMaxTime": 1506715200
      },
      {
        "time": 1506744000,
        "summary": "Light rain overnight.",
        "icon": "rain",
        "sunriseTime": 1506768759,
        "sunsetTime": 1506811269,
        "moonPhase": 0.33,
        "precipIntensity": 0.001,
        "precipIntensityMax": 0.0121,
        "precipIntensityMaxTime": 1506826800,
        "precipProbability": 0.08,
        "precipType": "rain",
        "temperatureHigh": 71.85,
        "temperatureHighTime": 1506801600,
        "temperatureLow": 60.03,
        "temperatureLowTime": 1506855600,
        "apparentTemperatureHigh": 71.85,
        "apparentTemperatureHighTime": 1506801600,
        "apparentTemperatureLow": 60.03,
        "apparentTemperatureLowTime": 1506855600,
        "dewPoint": 43.76,
        "humidity": 0.47,
        "pressure": 1019.28,
        "windSpeed": 6.37,
        "windGust": 26.12,
        "windGustTime": 1506744000,
        "windBearing": 286,
        "cloudCover": 0.02,
        "uvIndex": 5,
        "uvIndexTime": 1506790800,
        "ozone": 299.94,
        "temperatureMin": 59.09,
        "temperatureMinTime": 1506769200,
        "temperatureMax": 71.85,
        "temperatureMaxTime": 1506801600,
        "apparentTemperatureMin": 59.09,
        "apparentTemperatureMinTime": 1506769200,
        "apparentTemperatureMax": 71.85,
        "apparentTemperatureMaxTime": 1506801600
      },
      {
        "time": 1506830400,
        "summary": "Clear throughout the day.",
        "icon": "clear-day",
        "sunriseTime": 1506855220,
        "sunsetTime": 1506897569,
        "moonPhase": 0.36,
        "precipIntensity": 0.0011,
        "precipIntensityMax": 0.007,
        "precipIntensityMaxTime": 1506830400,
        "precipProbability": 0.22,
        "precipType": "rain",
        "temperatureHigh": 72.34,
        "temperatureHighTime": 1506884400,
        "temperatureLow": 60.17,
        "temperatureLowTime": 1506934800,
        "apparentTemperatureHigh": 72.34,
        "apparentTemperatureHighTime": 1506884400,
        "apparentTemperatureLow": 60.17,
        "apparentTemperatureLowTime": 1506934800,
        "dewPoint": 47.31,
        "humidity": 0.52,
        "pressure": 1024.02,
        "windSpeed": 2.04,
        "windGust": 12.74,
        "windGustTime": 1506902400,
        "windBearing": 89,
        "cloudCover": 0,
        "uvIndex": 5,
        "uvIndexTime": 1506873600,
        "ozone": 293.46,
        "temperatureMin": 60.03,
        "temperatureMinTime": 1506855600,
        "temperatureMax": 72.34,
        "temperatureMaxTime": 1506884400,
        "apparentTemperatureMin": 60.03,
        "apparentTemperatureMinTime": 1506855600,
        "apparentTemperatureMax": 72.34,
        "apparentTemperatureMaxTime": 1506884400
      }
    ]
  },
  "geo-data": {
    "address": "455 Graham Ave. Brooklyn, NY 11222"
  }
}
